{
  "colors": {
    "main": {
      "picollo": {
        "value": "#4E46B4",
        "type": "color"
      },
      "hit": {
        "value": "#40A69F",
        "type": "color"
      },
      "beerus": {
        "value": "#444444",
        "type": "color"
      },
      "goku": {
        "value": "#0B0B0B",
        "type": "color"
      },
      "gohan": {
        "value": "#1F1F1F",
        "type": "color"
      },
      "bulma": {
        "value": "#FFFFFF",
        "type": "color"
      },
      "trunks": {
        "value": "#7b7e83",
        "type": "color"
      },
      "goten": {
        "value": "#FFFFFF",
        "type": "color"
      },
      "popo": {
        "value": "#000000",
        "type": "color"
      },
      "jiren": {
        "value": "#28273d",
        "type": "color"
      },
      "hales": {
        "value": "#FFFFFF10",
        "type": "color"
      },
      "zeno": {
        "value": "#00000056",
        "type": "color"
      }
    }
  }
}
